{"name": "บริษัท เอฟเอซี คอนสตรัคชั่น จำกัด", "tin": "0205550006624", "totalProjects": 1, "projects": [{"projectId": "61027351408", "projectName": "ประกวดราคาจ้างก่อสร้างลอกท่อรวบรวมน้ำเสียและสถานีสูบน้ำขนาดเล็กเพื่อการท่องเที่ยวทางประวัติศาสตร์ เทศบาลนครพระนครศรีอยุธยา อำเภอพระนครศรีอยุธยา จังหวัดพระนครศรีอยุธยา ด้วยวิธีประกวดราคาอิเล็กทรอนิกส์ (e-bidding)", "localAuthority": "เทศบาลนครพระนครศรีอยุธยา", "province": "พระนครศรีอยุธยา", "projectValue": 25000000.0, "purchaseMethod": "ประกวดราคาอิเล็กทรอนิกส์ (e-bidding)"}]}