{"name": "พี. เอ็น. เค. คอนสตรัคชั่น", "tin": "0905545000536", "totalProjects": 5, "projects": [{"projectId": "61067191854", "projectName": "ประกวดราคาจ้างก่อสร้างถนนลาดยางพร้อมท่อระบายน้ำ (ธนชาติ)  หมู่ที่ 2  ตำบลเกาะแก้ว อำเภอเมือง จังหวัดภูเก็ต ด้วยวิธีประกวดราคาอิเล็กทรอนิกส์ (e-bidding)", "localAuthority": "องค์การบริหารส่วนตำบลเกาะแก้ว", "province": "ภูเก็ต", "projectValue": 12000000.0, "purchaseMethod": "ประกวดราคาอิเล็กทรอนิกส์ (e-bidding)"}, {"projectId": "61027091706", "projectName": "ประกวดราคาจ้างก่อสร้างปรับปรุงผิวจราจรทางแยกต่างๆ ภายในเขตเทศบาลนครภูเก็ต ด้วยวิธีประกวดราคาอิเล็กทรอนิกส์ (e-bidding)", "localAuthority": "เทศบาลนครภูเก็ต", "province": "ภูเก็ต", "projectValue": 6350000.0, "purchaseMethod": "ประกวดราคาอิเล็กทรอนิกส์ (e-bidding)"}, {"projectId": "61027471822", "projectName": "สอบราคาจ้างปรับปรุงผิวจราจรถนนทางหลวงท้องถิ่น พง.ถ.๑๐๐๕ สายเพชรเกษม-บ้านโคกเจริญ อำเภอทับปุด จังหวัดพังงา", "localAuthority": "องค์การบริหารส่วนจังหวัดพังงา", "province": "พังงา", "projectValue": 2000000.0, "purchaseMethod": "สอบราคา"}, {"projectId": "61027344785", "projectName": "สอบราคาจ้างปรับปรุงเสริมผิวทางพาราแอสฟัลท์คอนกรีต ซอยสุขสะอาด-วิเชียรสร้าง หมู่ที่ 3 ตำบลคุระ อำเภอคุระบุรี จังหวัดพังงา", "localAuthority": "องค์การบริหารส่วนตำบลคุระ", "province": "พังงา", "projectValue": 1750000.0, "purchaseMethod": "สอบราคา"}, {"projectId": "61057040145", "projectName": "สอบราคาจ้างก่อสร้างถนนพาราแอสฟัลท์คอนกรีต ซอยคลองแห้ง หมู่ที่ 4 ตำบลคุระ อำเภอคุระบุรี จังหวัดพังงา", "localAuthority": "องค์การบริหารส่วนตำบลคุระ", "province": "พังงา", "projectValue": 1064000.0, "purchaseMethod": "สอบราคา"}]}